arithmetic_netlists/muliplier/8-bit unsigned modified booth multiplier with CLA_ripple adder/dff_us.v
//21-bit dff with synchronous active-high reset
module dff_us(q,d,clk,rst);
	output reg [20:0] q;	
	input [20:0] d;
	input clk,rst;
	always @(posedge clk)
	begin
	if(rst)
		q <= 21'd0;
	else
		q <= d;
	end
endmodule

arithmetic_netlists/muliplier/8-bit unsigned modified booth multiplier with CLA_ripple adder/sum.v
//Generates the sum in a 4-bit CLA once the carries are simultaneously generated using the carry module.
module sum(s,p,c);
	output [3:0] s;
	input [3:0]  p,c;
	assign s = p^c;
endmodule

arithmetic_netlists/muliplier/16-bit unsigned multiplier using wallace tree/carry.v
module carry(c1,c2,c3,c4,p,g,c0);
	output c1,c2,c3,c4;
	input [3:0] p,g;
	input c0;
	assign c1 = g[0] | c0&p[0] ; 
	assign c2 = g[1] | g[0]&p[1] | c0&p[0]&p[1];
	assign c3 = g[2] | g[1]&p[2] | g[0]&p[1]&p[2] | c0&p[0]&p[1]&p[2];
	assign c4 = g[3] | g[2]&p[3] | g[1]&p[2]&p[3] | g[0]&p[1]&p[2]&p[3] | c0&p[0]&p[1]&p[2]&p[3];
endmodule

arithmetic_netlists/muliplier/8-bit modified booth multiplier with CLA_ripple adder/carry_prop_gen.v
//Generates carry propogate and carry generate given two input nos. refer CLA theory.
module carry_prop_gen(p,g,a,b);
	output [3:0] p,g;
	input [3:0] a,b;
	assign p = a^b;
	assign g = a&b;
endmodule

arithmetic_netlists/muliplier/8-bit unsigned modified booth multiplier with CLA_ripple adder/cla_ripple_12bit.v
//12-bit CLA built using three 4-bit CLAs with a ripple carry between individual CLAs. Adder can function as a subtractor depending on the control signal. (a + b) or (a-b)
`include "mux_2x1.v"
`include "carry.v"
`include "carry_prop_gen.v"
`include "sum.v"

module cla_ripple_12bit(sum,c12,a,b,c0);
	output [11:0] sum;
	output c12;
	input [11:0] a,b;
	input c0;
	wire c4;
	wire c8;
	wire [11:0] b2;
	mux_2x1 m2x1(.dout(b2),.d0(b),.d1((~b)),.sel(c0));
	cla_4bit_2 c4b1(.sum(sum[3:0]),.c4(c4),.a(a[3:0]),.b(b2[3:0]),.c0(c0));
	cla_4bit_2 c4b2(.sum(sum[7:4]),.c4(c8),.a(a[7:4]),.b(b2[7:4]),.c0(c4));
	cla_4bit_2 c4b3(.sum(sum[11:8]),.c4(c12),.a(a[11:8]),.b(b2[11:8]),.c0(c8));
endmodule


/*
module cla_ripple_8bit(sum,c8,a,b,c0);
	output [7:0] sum;
	output c8;
	input [7:0] a,b;
	input c0;
	wire c4;
	wire [7:0] b2;
	mux_2x1 m2x1(.dout(b2),.d0(b),.d1((~b)),.sel(c0));
	cla_4bit_2 c4b1(.sum(sum[3:0]),.c4(c4),.a(a[3:0]),.b(b2[3:0]),.c0(c0));
	cla_4bit_2 c4b2(.sum(sum[7:4]),.c4(c8),.a(a[7:4]),.b(b2[7:4]),.c0(c4));
endmodule
*/

module cla_4bit_2(sum,c4,a,b,c0);
	output [3:0] sum;
	output c4;
	input [3:0] a,b;
	input c0;
	wire [3:0] p,g;
	wire c1,c2,c3;
	carry_prop_gen cpg1(.p(p),.g(g),.a(a),.b(b));
	carry ca1(.c1(c1),.c2(c2),.c3(c3),.c4(c4),.p(p),.g(g),.c0(c0));
	sum s1(.s(sum),.p(p),.c({c3,c2,c1,c0}));
endmodule


/*
module tb_cla_ripple_8bit();
	reg [7:0] a,b;
	reg c0;
	wire [7:0] d;
	wire cout;
	cla_ripple_8bit uut(.sum(d),.c8(cout),.a(a),.b(b),.c0(c0));
	
	initial
	begin
	#00 a=8'd10; b=8'd10; c0 = 1'b0; //10-2
	#20 a=8'd30; b=8'd20; c0 = 1'b1;
	#20 a=8'd150; b=8'd130; c0 = 1'b1; //3-5
	#20 a=8'd255; b=8'd255; c0 = 1'b1;
	#20 $stop;
	end
	
	initial
	begin
	$monitor("time=%3d, a=%8d, b=%8d, co=%b, d=%8d, cout=%1b",$time,a,b,c0,d,cout);
	end
		
	initial
	begin
	$dumpfile("cla.vcd");
	$dumpvars;
	end
	
endmodule
*/

/*
module tb_cla_4bit();
	reg [3:0] a,b;
	reg c0;
	wire [3:0] d;
	wire cout;
	cla_4bit uut(.sum(d),.c4(cout),.a(a),.b(b),.c0(c0));
	
	initial
	begin
	#00 a=4'd10; b=4'b1101; c0 = 1'b1; //10-2
	#20 a=4'd10; b=4'b0101; c0 = 1'b1;
	#20 a=4'd3; b=4'b1010; c0 = 1'b1; //3-5
	#20 a=4'd15; b=4'd0; c0 = 1'b1;
	#20 $stop;
	end
	
	initial
	begin
	$monitor("time=%3d, a=%4d, b=%4d, co=%b, d=%4d, cout=%1b",$time,a,b,c0,d,cout);
	end
		
	initial
	begin
	$dumpfile("cla.vcd");
	$dumpvars;
	end
	
endmodule
*/

arithmetic_netlists/muliplier/8-bit unsigned modified booth multiplier with CLA_ripple adder/mux_2x1.v
//do if sel is 0 else d1. 12 bit mux
module mux_2x1(dout,d0,d1,sel);
	output [11:0] dout;
	input [11:0] d0,d1;
	input sel;
	assign dout = sel ? d1 : d0;
endmodule

arithmetic_netlists/muliplier/8-bit unsigned modified booth multiplier with CLA_ripple adder/accumulator_us.v
`include "cla_ripple_12bit.v"
`include "dff_us.v"
//Accumlates the partial products and shifts them by 2-bits every clock cycle. refer arch. Different from signed multiplier module since the accumulation happens for a 10-bit input number/
module accumulator_us(res,md,cla_sub,load,clk,rst);
	output [15:0] res;
	input [10:0] md;
	input clk,rst,load,cla_sub;
	
	wire [20:0] par_res, shift_par_res, reg_res;
	wire [11:0] cla_res;
	wire rst_new;
	cla_ripple_12bit cr12b1(.sum(cla_res),.c12(x),.a({1'b0,reg_res[20:10]}),.b({1'd0,md}),.c0(cla_sub));
	assign par_res[20:10] =  cla_res[10:0];
	assign par_res[9:0] = reg_res[9:0];
	assign shift_par_res = {par_res[20],par_res[20],par_res[20:2]};
	assign rst_new = rst | load;
	dff_us d1(.q(reg_res),.d(shift_par_res),.clk(clk),.rst(rst_new));
	assign res = reg_res[15:0];
endmodule

arithmetic_netlists/muliplier/8-bit unsigned modified booth multiplier with CLA_ripple adder/mux_4x1_us.v
//11-bit 4x1 mux
module mux_4x1_us(dout,d0,d1,d2,d3,sel);
	output reg [10:0] dout;
	input [10:0] d0,d1,d2,d3;
	input [1:0] sel;
	always @(*)
	begin
		case(sel)
		2'b00: dout <= d0;
		2'b01: dout <= d1;
		2'b10: dout <= d2;
		2'b11: dout <= d3;
		default: dout <= 11'dz;
		endcase
	end
endmodule

arithmetic_netlists/muliplier/8-bit unsigned modified booth multiplier with CLA_ripple adder/reco_unit_us.v
//Recoding unit for radix-4 booth's algorithm
// op = 0 => 0
// op = 1 => A
// op = 2 => 2A
// sign = 0 => Add
// sign = 1 => Subtract
module reco_unit_us(op,sign,xi);
	output reg [1:0] op;
	output reg sign;
	input [2:0] xi;
	always @(*)
	begin
		case(xi)
		3'b000: begin op <= 2'd0; sign <= 1'd0; end //0
		3'b010: begin op <= 2'd1; sign <= 1'd0; end //+A
		3'b100: begin op <= 2'd2; sign <= 1'd1; end //-2A
		3'b110: begin op <= 2'd1; sign <= 1'd1; end //-A
		3'b001: begin op <= 2'd1; sign <= 1'd0; end //+A
		3'b011: begin op <= 2'd2; sign <= 1'd0; end //+2A
		3'b101: begin op <= 2'd1; sign <= 1'd1; end //-A
		3'b111: begin op <= 2'd0; sign <= 1'd0; end //0
		default: begin op <= 2'dz; sign <= 1'dz; end 
		endcase
	end

endmodule

arithmetic_netlists/muliplier/8-bit unsigned modified booth multiplier with CLA_ripple adder/piso_2bit_us.v
//8 bit PISO with synchronous reset and active high load pin. When load is zero, it shifts in serial 2 bits at a time. When load is one, it loads in parallel. 
`timescale 1ns/10ps
module piso_2bit_us(sout,pin,load,clk,rst);
    output reg [2:0] sout;
    input [9:0] pin;
    input load,clk,rst;
    reg [10:0] dout;
    always @(posedge clk)
        begin
            if(rst)
				begin
                dout = 11'd0;
				sout = 3'b0;
				end
            else if(load)
				begin
                dout = {pin,1'b0};
				sout = dout[2:0];
				end
            else
                begin
                    dout = {2'b0,dout[10:2]};
					sout = dout[2:0];
                end
        end
endmodule

arithmetic_netlists/muliplier/8-bit unsigned modified booth multiplier with CLA_ripple adder/multi_8bit_unsigned.v
//8-bit Radix-4 booth unsigned multiplier. a - Multiplicand. b - Multiplier
// Partial products generated using a radix-4 modified booth algorithm
//Partial products produced sequentially using three 4-bit CLA modules with carries rippling across them.
`include "piso_2bit_us.v"
`include "reco_unit_us.v"
`include "mux_4x1_us.v"
`include "accumulator_us.v"

module multi_8bit_unsigned(prod,a,b,clk,rst,load);
	output [15:0] prod;
	input [7:0] a,b;
	input clk,rst,load;
	wire [2:0] xi;
	wire [1:0] mr_sel;
	wire cla_sub; 
	wire [10:0] md;
	wire [9:0] ad,bd;
	assign ad = {2'd0,a};
	assign bd = {2'd0,b};
	piso_2bit_us p2b1(.sout(xi),.pin(bd),.load(load),.clk(clk),.rst(rst));
	reco_unit_us ru(.op(mr_sel),.sign(cla_sub),.xi(xi));
	mux_4x1_us m41(.dout(md),.d0(11'd0),.d1({ad[9],ad}),.d2({ad,1'b0}),.d3(11'd0),.sel(mr_sel));
	accumulator_us a1(.res(prod),.md(md),.cla_sub(cla_sub),.load(load),.clk(clk),.rst(rst));
endmodule


module tb_multi_8bit_unsigned();
	reg [7:0] a,b;
	reg clk,rst,load;
	wire [15:0] prod;
	multi_8bit_unsigned uut(.prod(prod),.a(a),.b(b),.clk(clk),.rst(rst),.load(load));
	
	initial
	begin
	#00 clk = 1'b0;
	forever #50 clk = ~clk;
	end
	
	initial
	begin
	#00 rst = 1'b1;
	#60 rst = 1'b0;
	end
	
	initial
	begin
	#110 load = 1'b1; a = 8'd255; b = 8'd230;
	# 60 load = 1'b0; 
	
	#570 load = 1'b1; a = 8'd5; b = 8'd9; //at 740 ps
	# 20 load = 1'b0; //at 760 ps. result out at 1050 ps.
	#580 load = 1'b1; a = 8'd150; b = 8'd100;
	# 20 load = 1'b0;
	#580 load = 1'b1; a = 8'd200; b = 8'd250;
	# 20 load = 1'b0;
	#580 load = 1'b1; a = 8'd233; b = 8'd111;
	# 20 load = 1'b0;
	#580 load = 1'b1; a = 8'd55; b = 8'd46;
	# 20 load = 1'b0;
	#580 load = 1'b1; a = 8'd255; b = 8'd255;
	# 20 load = 1'b0;
	#580 $stop;

	/*
	#480 load = 1'b1; a = 8'd13; b = 8'd15;
	# 20 load = 1'b0;
	#480 load = 1'b1; a = 8'd13; b = 8'd15;
	# 20 load = 1'b0;
	#480 load = 1'b1; a = 8'd13; b = 8'd15;
	# 20 load = 1'b0;
	#480 load = 1'b1; a = 8'd13; b = 8'd15;
	# 20 load = 1'b0;
	#480 load = 1'b1; a = 8'd13; b = 8'd15;
	# 20 load = 1'b0;
	*/
	
	end
	
	
	initial
	begin
	$dumpfile("multi_8bit_unsigned.vcd");
	$dumpvars;
	end
	
endmodule

arithmetic_netlists/muliplier/8-bit unsigned modified booth multiplier with CLA_ripple adder/multi_8bit_unsigned.vcd
$date
	Wed May 02 09:39:11 2018
$end
$version
	Icarus Verilog
$end
$timescale
	10ps
$end
$scope module tb_multi_8bit_unsigned $end
$var wire 16 ! prod [15:0] $end
$var reg 8 " a [7:0] $end
$var reg 8 # b [7:0] $end
$var reg 1 $ clk $end
$var reg 1 % load $end
$var reg 1 & rst $end
$scope module uut $end
$var wire 8 ' a [7:0] $end
$var wire 8 ( b [7:0] $end
$var wire 1 $ clk $end
$var wire 1 % load $end
$var wire 1 & rst $end
$var wire 3 ) xi [2:0] $end
$var wire 16 * prod [15:0] $end
$var wire 2 + mr_sel [1:0] $end
$var wire 11 , md [10:0] $end
$var wire 1 - cla_sub $end
$var wire 10 . bd [9:0] $end
$var wire 10 / ad [9:0] $end
$scope module a1 $end
$var wire 1 $ clk $end
$var wire 1 % load $end
$var wire 1 & rst $end
$var wire 1 0 rst_new $end
$var wire 1 1 x $end
$var wire 21 2 shift_par_res [20:0] $end
$var wire 16 3 res [15:0] $end
$var wire 21 4 reg_res [20:0] $end
$var wire 21 5 par_res [20:0] $end
$var wire 11 6 md [10:0] $end
$var wire 1 - cla_sub $end
$var wire 12 7 cla_res [11:0] $end
$scope module cr12b1 $end
$var wire 12 8 a [11:0] $end
$var wire 12 9 b [11:0] $end
$var wire 12 : sum [11:0] $end
$var wire 1 ; c8 $end
$var wire 1 < c4 $end
$var wire 1 1 c12 $end
$var wire 1 - c0 $end
$var wire 12 = b2 [11:0] $end
$scope module c4b1 $end
$var wire 4 > a [3:0] $end
$var wire 4 ? b [3:0] $end
$var wire 4 @ sum [3:0] $end
$var wire 4 A p [3:0] $end
$var wire 4 B g [3:0] $end
$var wire 1 < c4 $end
$var wire 1 C c3 $end
$var wire 1 D c2 $end
$var wire 1 E c1 $end
$var wire 1 - c0 $end
$scope module ca1 $end
$var wire 1 E c1 $end
$var wire 1 D c2 $end
$var wire 1 C c3 $end
$var wire 1 < c4 $end
$var wire 4 F p [3:0] $end
$var wire 4 G g [3:0] $end
$var wire 1 - c0 $end
$upscope $end
$scope module cpg1 $end
$var wire 4 H a [3:0] $end
$var wire 4 I b [3:0] $end
$var wire 4 J g [3:0] $end
$var wire 4 K p [3:0] $end
$upscope $end
$scope module s1 $end
$var wire 4 L c [3:0] $end
$var wire 4 M p [3:0] $end
$var wire 4 N s [3:0] $end
$upscope $end
$upscope $end
$scope module c4b2 $end
$var wire 4 O a [3:0] $end
$var wire 4 P b [3:0] $end
$var wire 1 < c0 $end
$var wire 4 Q sum [3:0] $end
$var wire 4 R p [3:0] $end
$var wire 4 S g [3:0] $end
$var wire 1 ; c4 $end
$var wire 1 T c3 $end
$var wire 1 U c2 $end
$var wire 1 V c1 $end
$scope module ca1 $end
$var wire 1 < c0 $end
$var wire 1 V c1 $end
$var wire 1 U c2 $end
$var wire 1 T c3 $end
$var wire 1 ; c4 $end
$var wire 4 W p [3:0] $end
$var wire 4 X g [3:0] $end
$upscope $end
$scope module cpg1 $end
$var wire 4 Y a [3:0] $end
$var wire 4 Z b [3:0] $end
$var wire 4 [ g [3:0] $end
$var wire 4 \ p [3:0] $end
$upscope $end
$scope module s1 $end
$var wire 4 ] c [3:0] $end
$var wire 4 ^ p [3:0] $end
$var wire 4 _ s [3:0] $end
$upscope $end
$upscope $end
$scope module c4b3 $end
$var wire 4 ` a [3:0] $end
$var wire 4 a b [3:0] $end
$var wire 1 ; c0 $end
$var wire 4 b sum [3:0] $end
$var wire 4 c p [3:0] $end
$var wire 4 d g [3:0] $end
$var wire 1 1 c4 $end
$var wire 1 e c3 $end
$var wire 1 f c2 $end
$var wire 1 g c1 $end
$scope module ca1 $end
$var wire 1 ; c0 $end
$var wire 1 g c1 $end
$var wire 1 f c2 $end
$var wire 1 e c3 $end
$var wire 1 1 c4 $end
$var wire 4 h p [3:0] $end
$var wire 4 i g [3:0] $end
$upscope $end
$scope module cpg1 $end
$var wire 4 j a [3:0] $end
$var wire 4 k b [3:0] $end
$var wire 4 l g [3:0] $end
$var wire 4 m p [3:0] $end
$upscope $end
$scope module s1 $end
$var wire 4 n c [3:0] $end
$var wire 4 o p [3:0] $end
$var wire 4 p s [3:0] $end
$upscope $end
$upscope $end
$scope module m2x1 $end
$var wire 12 q d0 [11:0] $end
$var wire 12 r d1 [11:0] $end
$var wire 1 - sel $end
$var wire 12 s dout [11:0] $end
$upscope $end
$upscope $end
$scope module d1 $end
$var wire 1 $ clk $end
$var wire 21 t d [20:0] $end
$var wire 1 0 rst $end
$var reg 21 u q [20:0] $end
$upscope $end
$upscope $end
$scope module m41 $end
$var wire 11 v d0 [10:0] $end
$var wire 11 w d1 [10:0] $end
$var wire 11 x d2 [10:0] $end
$var wire 11 y d3 [10:0] $end
$var wire 2 z sel [1:0] $end
$var reg 11 { dout [10:0] $end
$upscope $end
$scope module p2b1 $end
$var wire 1 $ clk $end
$var wire 1 % load $end
$var wire 10 | pin [9:0] $end
$var wire 1 & rst $end
$var reg 11 } dout [10:0] $end
$var reg 3 ~ sout [2:0] $end
$upscope $end
$scope module ru $end
$var wire 3 !" xi [2:0] $end
$var reg 2 "" op [1:0] $end
$var reg 1 - sign $end
$upscope $end
$upscope $end
$upscope $end
$enddefinitions $end
#0
$dumpvars
bx ""
bx !"
bx ~
bx }
b0xxxxxxxx |
bz {
bx z
b0 y
b0xxxxxxxx0 x
b0xxxxxxxx w
b0 v
bx u
bx t
bx s
b1xxxxxxxxxxx r
b0zzzzzzzzzzz q
bx p
bx o
bx n
bx m
b0xxx l
bx k
b0xxx j
b0xxx i
bx h
xg
xf
xe
b0xxx d
bx c
bx b
bx a
b0xxx `
bx _
bx ^
bx ]
bx \
bx [
bx Z
bx Y
bx X
bx W
xV
xU
xT
bx S
bx R
bx Q
bx P
bx O
bx N
bx M
bx L
bx K
bx J
bx I
bx H
bx G
bx F
xE
xD
xC
bx B
bx A
bx @
bx ?
bx >
bx =
x<
x;
bx :
b0zzzzzzzzzzz 9
b0xxxxxxxxxxx 8
bx 7
bz 6
bx 5
bx 4
bx 3
bx 2
x1
10
b0xxxxxxxx /
b0xxxxxxxx .
x-
bz ,
bx +
bx *
bx )
bx (
bx '
1&
x%
0$
bx #
bx "
bx !
$end
#5000
b0 Q
b0 _
b0 @
b0 N
b0 R
b0 W
b0 \
b0 ^
b0 A
b0 F
b0 K
b0 M
b111111111111 r
b0 9
b0 q
b0 ,
b0 6
b0 {
b0 7
b0 :
b0 b
b0 p
0e
0f
0g
b0 n
0;
0T
0U
0V
b0 ]
0<
0C
0D
01
0E
b0 B
b0 G
b0 J
b0 S
b0 X
b0 [
b0 c
b0 h
b0 m
b0 o
b0 d
b0 i
b0 l
b0 a
b0 k
b0 P
b0 Z
b0 ?
b0 I
b0 2
b0 t
b0 >
b0 H
b0 O
b0 Y
b0 `
b0 j
b0 =
b0 s
b0 !
b0 *
b0 3
b0 5
b0 8
b0 L
0-
b0 +
b0 z
b0 ""
b0 4
b0 u
b0 )
b0 ~
b0 !"
b0 }
1$
#6000
x0
0&
#10000
0$
#11000
10
b11100110 .
b11100110 |
b11100110 #
b11100110 (
b11111111 w
b111111110 x
b11111111 /
b11111111 "
b11111111 '
1%
#15000
b111000000001 r
b111111110 9
b111111110 q
b111111110 ,
b111111110 6
b111111110 {
01
0e
0f
0g
b0 n
0;
0T
0U
0V
b0 ]
0<
0C
0D
1E
b1110 b
b1110 p
b0 Q
b0 _
b1110 c
b1110 h
b1110 m
b1110 o
b0 R
b0 W
b0 \
b0 ^
b1 A
b1 F
b1 K
b1 M
b111100000001000000000 2
b111100000001000000000 t
b1110 a
b1110 k
b0 P
b0 Z
b1 ?
b1 I
b110000000100000000000 5
b111000000001 =
b111000000001 s
b111000000010 7
b111000000010 :
b10 @
b10 N
b11 L
1-
b10 +
b10 z
b10 ""
b100 )
b100 ~
b100 !"
b111001100 }
1$
#17000
00
0%
#20000
0$
#25000
1;
1e
1f
b1111 n
1g
b111 Q
b111 _
b1001 b
b1001 p
b1110 A
b1110 F
b1110 K
b1110 M
b111 R
b111 W
b111 \
b111 ^
b1000 S
b1000 X
b1000 [
b110 c
b110 h
b110 m
b110 o
b1 d
b1 i
b1 l
b1 a
b1 k
b1111 P
b1111 Z
b1110 ?
b1110 I
0E
b10111111010000000 2
b10111111010000000 t
b1000 O
b1000 Y
b111 `
b111 j
b111111110 =
b111111110 s
b100101111110 7
b100101111110 :
b1110 @
b1110 N
b1000000000 !
b1000000000 *
b1000000000 3
b1011111101000000000 5
b11110000000 8
b0 L
0-
b111100000001000000000 4
b111100000001000000000 u
b11 )
b11 ~
b11 !"
b1110011 }
1$
#30000
0$
#35000
1V
b11 ]
1<
1C
0;
0e
1D
01
0f
1E
b0 n
0g
b110 Q
b110 _
b1110 b
b1110 p
b1 B
b1 G
b1 J
b101 R
b101 W
b101 \
b101 ^
b0 S
b0 X
b0 [
b1110 c
b1110 h
b1110 m
b1110 o
b0 d
b0 i
b0 l
b1110 a
b1110 k
b0 P
b0 Z
b1 ?
b1 I
b111100110000110100000 2
b111100110000110100000 t
b1111 >
b1111 H
b101 O
b101 Y
b0 `
b0 j
b111000000001 =
b111000000001 s
b111001100001 7
b111001100001 :
b1 @
b1 N
b111111010000000 !
b111111010000000 *
b111111010000000 3
b110011000011010000000 5
b1011111 8
b1111 L
1-
b10111111010000000 4
b10111111010000000 u
b100 )
b100 ~
b100 !"
b11100 }
1$
#40000
0$
#45000
0<
0V
b111111111111 r
b0 9
b0 q
b0 ,
b0 6
b0 {
0C
0;
0T
0e
0D
b0 ]
0U
0f
0E
b0 n
0g
b1001 Q
b1001 _
b111 b
b111 p
b1000 A
b1000 F
b1000 K
b1000 M
b0 B
b0 G
b0 J
b1001 R
b1001 W
b1001 \
b1001 ^
b0 S
b0 X
b0 [
b111 c
b111 h
b111 m
b111 o
b0 d
b0 i
b0 l
b0 a
b0 k
b0 P
b0 Z
b0 ?
b0 I
b111111001100001101000 2
b111111001100001101000 t
b1000 >
b1000 H
b1001 O
b1001 Y
b111 `
b111 j
b0 =
b0 s
b11110011000 7
b11110011000 :
b1000 @
b1000 N
b110000110100000 !
b110000110100000 *
b110000110100000 3
b111100110000110100000 5
b11110011000 8
b0 L
0-
b0 +
b0 z
b0 ""
b111100110000110100000 4
b111100110000110100000 u
b111 )
b111 ~
b111 !"
b111 }
1$
#50000
0$
#55000
1e
1f
1V
1g
b1000 b
b1000 p
1<
b1111 n
1;
1T
1C
b1111 ]
1U
b1100 L
1D
b1110 S
b1110 X
b1110 [
b110 B
b110 G
b110 J
b1111 P
b1111 Z
b1111 ?
b1111 I
b111100000000 r
b11111111 =
b11111111 s
b11111111 9
b11111111 q
b11111111 ,
b11111111 6
b11111111 {
b101 @
b101 N
b100011100101 7
b100011100101 :
b1110 Q
b1110 _
b1001 A
b1001 F
b1001 K
b1001 M
b1 R
b1 W
b1 \
b1 ^
b1110010100011010 2
b1110010100011010 t
b110 >
b110 H
b1110 O
b1110 Y
b1001100001101000 !
b1001100001101000 *
b1001100001101000 3
b111001010001101000 5
b11111100110 8
b1 +
b1 z
b1 ""
b111111001100001101000 4
b111111001100001101000 u
b1 )
b1 ~
b1 !"
b1 }
1$
#60000
0$
#65000
0U
0;
0<
0C
0V
b0 P
b0 Z
b0 ?
b0 I
b111111111111 r
b0 =
b0 s
b0 9
b0 q
b0 ,
b0 6
b0 {
b0 ]
0T
0D
0e
0f
b0 n
0g
b0 L
0E
b1001 @
b1001 N
b11 Q
b11 _
b111001 7
b111001 :
b0 b
b0 p
b1001 A
b1001 F
b1001 K
b1001 M
b0 B
b0 G
b0 J
b11 R
b11 W
b11 \
b11 ^
b0 S
b0 X
b0 [
b0 c
b0 h
b0 m
b0 o
b11100101000110 2
b11100101000110 t
b1001 >
b1001 H
b11 O
b11 Y
b0 `
b0 j
b1110010100011010 !
b1110010100011010 *
b1110010100011010 3
b1110010100011010 5
b111001 8
b0 +
b0 z
b0 ""
b1110010100011010 4
b1110010100011010 u
b0 )
b0 ~
b0 !"
b0 }
1$
#70000
0$
#74000
10
b1001 .
b1001 |
b1001 #
b1001 (
b101 w
b1010 x
b101 /
b101 "
b101 '
1%
#75000
b101 ?
b101 I
b111111111010 r
b101 =
b101 s
b101 9
b101 q
b101 ,
b101 6
b101 {
b101 @
b101 N
b101 7
b101 :
b0 Q
b0 _
b101 A
b101 F
b101 K
b101 M
b0 R
b0 W
b0 \
b0 ^
b10100000000 2
b10100000000 t
b0 >
b0 H
b0 O
b0 Y
b0 !
b0 *
b0 3
b1010000000000 5
b0 8
b1 +
b1 z
b1 ""
b0 4
b0 u
b10 )
b10 ~
b10 !"
b10010 }
1$
#76000
00
0%
#80000
0$
#85000
b1 B
b1 G
b1 J
b111111110101 r
b1010 9
b1010 q
b1010 ,
b1010 6
b1010 {
0D
b1111 b
b1111 p
b1111 Q
b1111 _
b1111 c
b1111 h
b1111 m
b1111 o
b1111 R
b1111 W
b1111 \
b1111 ^
b100 A
b100 F
b100 K
b100 M
b1111 a
b1111 k
b1111 P
b1111 Z
b101 ?
b101 I
1E
b111111111011101000000 2
b111111111011101000000 t
b1 >
b1 H
b111111110101 =
b111111110101 s
b111111110111 7
b111111110111 :
b111 @
b111 N
b10100000000 !
b10100000000 *
b10100000000 3
b111111101110100000000 5
b1 8
b11 L
1-
b10 +
b10 z
b10 ""
b10100000000 4
b10100000000 u
b100 )
b100 ~
b100 !"
b100 }
1$
#90000
0$
#95000
1C
b111111111010 r
b101 9
b101 q
b101 ,
b101 6
b101 {
1e
1f
1g
b1111 n
1;
1T
1U
1V
b0 Q
b0 _
b1111 ]
1<
1E
b1000 b
b1000 p
b1000 A
b1000 F
b1000 K
b1000 M
b101 B
b101 G
b101 J
b111 c
b111 h
b111 m
b111 o
b0 a
b0 k
b0 P
b0 Z
b101 ?
b101 I
b1011010000 2
b1011010000 t
b1101 >
b1101 H
b1111 O
b1111 Y
b111 `
b111 j
b101 =
b101 s
b100000000010 7
b100000000010 :
b10 @
b10 N
b1111011101000000 !
b1111011101000000 *
b1111011101000000 3
b101101000000 5
b11111111101 8
b1010 L
0-
b1 +
b1 z
b1 ""
b111111111011101000000 4
b111111111011101000000 u
b1 )
b1 ~
b1 !"
b1 }
1$
#100000
0$
#105000
b0 ?
b0 I
b111111111111 r
b0 =
b0 s
b0 9
b0 q
b0 ,
b0 6
b0 {
0<
0C
0;
0T
0U
b0 ]
0V
0e
0f
b0 n
0g
b0 L
0E
b0 @
b0 N
b0 Q
b0 _
b0 7
b0 :
b0 b
b0 p
b0 A
b0 F
b0 K
b0 M
b0 B
b0 G
b0 J
b0 R
b0 W
b0 \
b0 ^
b0 c
b0 h
b0 m
b0 o
b10110100 2
b10110100 t
b0 >
b0 H
b0 O
b0 Y
b0 `
b0 j
b1011010000 !
b1011010000 *
b1011010000 3
b1011010000 5
b0 8
b0 +
b0 z
b0 ""
b1011010000 4
b1011010000 u
b0 )
b0 ~
b0 !"
b0 }
1$
#110000
0$
#115000
b101101 2
b101101 t
b10110100 !
b10110100 *
b10110100 3
b10110100 5
b10110100 4
b10110100 u
1$
#120000
0$
#125000
b1011 2
b1011 t
b101101 !
b101101 *
b101101 3
b101101 5
b101101 4
b101101 u
1$
#130000
0$
#134000
10
b1100100 .
b1100100 |
b1100100 #
b1100100 (
b10010110 w
b100101100 x
b10010110 /
b10010110 "
b10010110 '
1%
#135000
b0 2
b0 t
b0 !
b0 *
b0 3
b0 5
b0 4
b0 u
b11001000 }
1$
#136000
00
0%
#140000
0$
#145000
b1001011000000000 2
b1001011000000000 t
b100101100000000000 5
b1001 Q
b1001 _
b10010110 7
b10010110 :
b110 @
b110 N
b1001 R
b1001 W
b1001 \
b1001 ^
b110 A
b110 F
b110 K
b110 M
b1001 P
b1001 Z
b110 ?
b110 I
b111101101001 r
b10010110 =
b10010110 s
b10010110 9
b10010110 q
b10010110 ,
b10010110 6
b10010110 {
b1 +
b1 z
b1 ""
b10 )
b10 ~
b10 !"
b110010 }
1$
#150000
0$
#155000
1C
1D
b111011010011 r
b100101100 9
b100101100 q
b100101100 ,
b100101100 6
b100101100 {
0T
b0 ]
0U
1E
b1110 b
b1110 p
b1111 Q
b1111 _
b1110 c
b1110 h
b1110 m
b1110 o
b110 A
b110 F
b110 K
b110 M
b1 B
b1 G
b1 J
b1111 R
b1111 W
b1111 \
b1111 ^
b0 S
b0 X
b0 [
b1110 a
b1110 k
b1101 P
b1101 Z
b11 ?
b11 I
b111101111100110000000 2
b111101111100110000000 t
b101 >
b101 H
b10 O
b10 Y
b111011010011 =
b111011010011 s
b111011111001 7
b111011111001 :
b1001 @
b1001 N
b1001011000000000 !
b1001011000000000 *
b1001011000000000 3
b110111110011000000000 5
b100101 8
b1111 L
1-
b10 +
b10 z
b10 ""
b1001011000000000 4
b1001011000000000 u
b100 )
b100 ~
b100 !"
b1100 }
1$
#160000
0$
#165000
1V
1<
1e
0D
1f
b111 ]
1U
0E
b1110 n
1g
b1110 Q
b1110 _
b1000 b
b1000 p
b10 A
b10 F
b10 K
b10 M
b1100 B
b1100 G
b1100 J
b1001 R
b1001 W
b1001 \
b1001 ^
b10 S
b10 X
b10 [
b110 c
b110 h
b110 m
b110 o
b1 d
b1 i
b1 l
b1 a
b1 k
b10 P
b10 Z
b1100 ?
b1100 I
b1110101001100000 2
b1110101001100000 t
b1110 >
b1110 H
b1011 O
b1011 Y
b111 `
b111 j
b100101100 =
b100101100 s
b100011101010 7
b100011101010 :
b1010 @
b1010 N
b1111100110000000 !
b1111100110000000 *
b1111100110000000 3
b111010100110000000 5
b11110111110 8
b1000 L
0-
b111101111100110000000 4
b111101111100110000000 u
b11 )
b11 ~
b11 !"
b11 }
1$
#170000
0$
#175000
0U
0V
b0 ]
0<
b0 S
b0 X
b0 [
b0 a
b0 k
b0 P
b0 Z
b0 ?
b0 I
b111111111111 r
b0 =
b0 s
b0 9
b0 q
b0 ,
b0 6
b0 {
b0 L
0C
0e
0f
b0 n
0g
b1010 @
b1010 N
b11 Q
b11 _
b111010 7
b111010 :
b0 b
b0 p
b1010 A
b1010 F
b1010 K
b1010 M
b0 B
b0 G
b0 J
b11 R
b11 W
b11 \
b11 ^
b0 c
b0 h
b0 m
b0 o
b0 d
b0 i
b0 l
b11101010011000 2
b11101010011000 t
b1010 >
b1010 H
b11 O
b11 Y
b0 `
b0 j
b1110101001100000 !
b1110101001100000 *
b1110101001100000 3
b1110101001100000 5
b111010 8
b0 +
b0 z
b0 ""
b1110101001100000 4
b1110101001100000 u
b0 )
b0 ~
b0 !"
b0 }
1$
#180000
0$
